fake_store/__init__.py
fake_store/binding.py
fake_store/load.py
fake_store/store.py
fake_store-0.2.dist-info/LICENSE
fake_store-0.2.dist-info/METADATA
fake_store-0.2.dist-info/WHEEL
fake_store-0.2.dist-info/top_level.txt
fake_store-0.2.dist-info/RECORD
