Metadata-Version: 2.1
Name: fake-store
Version: 0.2
Summary: UNKNOWN
Home-page: https://github.com/FabienArcellier/fake-store
License: MIT license
Platform: UNKNOWN
Classifier: Programming Language :: Python :: 3
Classifier: License :: OSI Approved :: MIT License
Classifier: Operating System :: OS Independent
Classifier: Intended Audience :: Developers
Classifier: Environment :: Console
License-File: LICENSE
Requires-Dist: pyyaml
Provides-Extra: dev
Requires-Dist: alfred-cli ; extra == 'dev'
Requires-Dist: build ; extra == 'dev'
Requires-Dist: pylint ; extra == 'dev'
Requires-Dist: coverage ; extra == 'dev'
Requires-Dist: twine ; extra == 'dev'
